{"stats":{"minecraft:killed_by":{"minecraft:zombie":2,"minecraft:skeleton":3},"minecraft:custom":{"minecraft:animals_bred":11,"minecraft:interact_with_crafting_table":159,"minecraft:open_barrel":454,"minecraft:open_shulker_box":674,"minecraft:bell_ring":37,"minecraft:leave_game":12,"minecraft:time_since_death":1024715,"minecraft:sprint_one_cm":2489387,"minecraft:drop":322,"minecraft:play_noteblock":2,"minecraft:talked_to_villager":197,"minecraft:play_time":1205028,"minecraft:deaths":5,"minecraft:jump":23385,"minecraft:interact_with_brewingstand":57,"minecraft:walk_on_water_one_cm":140632,"minecraft:enchant_item":139,"minecraft:interact_with_furnace":190,"minecraft:play_record":2,"minecraft:traded_with_villager":592,"minecraft:interact_with_loom":1,"minecraft:sleep_in_bed":2,"minecraft:open_enderchest":9,"minecraft:damage_dealt":258272,"minecraft:crouch_one_cm":253626,"minecraft:use_cauldron":19,"minecraft:interact_with_smithing_table":7,"minecraft:inspect_dropper":1,"minecraft:mob_kills":9454,"minecraft:interact_with_anvil":108,"minecraft:inspect_hopper":150,"minecraft:fill_cauldron":4,"minecraft:interact_with_campfire":3,"minecraft:climb_one_cm":252288,"minecraft:walk_one_cm":2632601,"minecraft:sneak_time":81087,"minecraft:walk_under_water_one_cm":316142,"minecraft:boat_one_cm":295922,"minecraft:interact_with_blast_furnace":71,"minecraft:total_world_time":1294825,"minecraft:tune_noteblock":59,"minecraft:interact_with_grindstone":55,"minecraft:interact_with_stonecutter":1,"minecraft:time_since_rest":344389,"minecraft:damage_taken":9194,"minecraft:damage_absorbed":41,"minecraft:minecart_one_cm":638921,"minecraft:swim_one_cm":52911,"minecraft:fly_one_cm":2972379,"minecraft:open_chest":1599,"minecraft:aviate_one_cm":4509476,"minecraft:fall_one_cm":225734},"minecraft:killed":{"minecraft:cave_spider":3,"minecraft:zombified_piglin":2704,"minecraft:witch":2,"minecraft:spider":69,"minecraft:skeleton":98,"minecraft:magma_cube":70,"minecraft:piglin":4,"minecraft:creeper":61,"minecraft:pillager":3,"minecraft:trader_llama":4,"minecraft:zombie":88,"minecraft:ghast":7,"minecraft:glow_squid":10,"minecraft:cow":4,"minecraft:blaze":9,"minecraft:phantom":44,"minecraft:drowned":33,"minecraft:husk":23,"minecraft:rabbit":1,"minecraft:bat":4,"minecraft:squid":1,"minecraft:wither_skeleton":14,"minecraft:enderman":5},"minecraft:broken":{"minecraft:golden_sword":26},"minecraft:dropped":{"minecraft:soul_sand":79,"minecraft:glass_bottle":1,"minecraft:flint":1,"minecraft:dirt":123,"minecraft:gold_nugget":4,"minecraft:phantom_membrane":16,"minecraft:gold_ingot":345,"minecraft:bone":20,"minecraft:gravel":43,"minecraft:blackstone":95,"minecraft:sugar_cane":2,"minecraft:iron_nugget":40,"minecraft:cobbled_deepslate":64,"minecraft:nether_brick":57,"minecraft:netherite_sword":1,"minecraft:wheat":2,"minecraft:rotten_flesh":237,"minecraft:carrot":31,"minecraft:poppy":1,"minecraft:arrow":1,"minecraft:quartz":128,"minecraft:netherrack":1637,"minecraft:bread":20,"minecraft:wheat_seeds":475,"minecraft:minecart":1,"minecraft:cobblestone":61,"minecraft:granite":5,"minecraft:coal":11,"minecraft:stick":8,"minecraft:diorite":3,"minecraft:potion":3,"minecraft:string":19,"minecraft:cobblestone_slab":1,"minecraft:andesite":1,"minecraft:oak_sapling":2,"minecraft:spider_eye":9},"minecraft:picked_up":{"minecraft:wheat":205,"minecraft:lead":7,"minecraft:diamond_sword":1,"minecraft:potion":10,"minecraft:enchanted_book":2,"minecraft:birch_button":1,"minecraft:nether_brick":86,"minecraft:stone_brick_stairs":24,"minecraft:golden_sword":105,"minecraft:polished_deepslate":9,"minecraft:music_disc_cat":1,"minecraft:string":248,"minecraft:raw_copper":4,"minecraft:cooked_salmon":3,"minecraft:sticky_piston":2,"minecraft:activator_rail":3,"minecraft:gold_nugget":1423,"minecraft:cobbled_deepslate":879,"minecraft:acacia_sign":2,"minecraft:redstone_torch":29,"minecraft:cobblestone_slab":29,"minecraft:calcite":1,"minecraft:furnace":1,"minecraft:stick":210,"minecraft:torch":83,"minecraft:acacia_log":45,"minecraft:diorite":19,"minecraft:golden_chestplate":1,"minecraft:cactus":25,"minecraft:rotten_flesh":1194,"minecraft:blaze_rod":11,"minecraft:obsidian":9,"minecraft:cobblestone":688,"minecraft:birch_log":1,"minecraft:magma_block":37,"minecraft:cooked_beef":8,"minecraft:magma_cream":31,"minecraft:repeater":1,"minecraft:water_bucket":1,"minecraft:andesite":27,"minecraft:flint":6,"minecraft:tuff":73,"minecraft:acacia_boat":2,"minecraft:wither_skeleton_skull":2,"minecraft:lapis_lazuli":531,"minecraft:dirt":2657,"minecraft:lantern":1,"minecraft:bone":237,"minecraft:acacia_planks":1,"minecraft:bow":15,"minecraft:wheat_seeds":1151,"minecraft:raw_gold":18,"minecraft:rabbit":1,"minecraft:bamboo":88,"minecraft:powered_rail":59,"minecraft:music_disc_13":1,"minecraft:sand":323,"minecraft:dropper":5,"minecraft:ink_sac":11,"minecraft:spectral_arrow":45,"minecraft:shulker_box":8,"minecraft:sugar":4,"minecraft:diamond":70,"minecraft:lever":4,"minecraft:granite":39,"minecraft:spruce_sign":1,"minecraft:bread":2,"minecraft:oak_sapling":2,"minecraft:netherrack":3516,"minecraft:crafting_table":4,"minecraft:splash_potion":4,"minecraft:nether_wart":5,"minecraft:ladder":1,"minecraft:acacia_door":1,"minecraft:item_frame":3,"minecraft:blackstone":234,"minecraft:detector_rail":25,"minecraft:netherite_sword":1,"minecraft:oak_boat":2,"minecraft:observer":5,"minecraft:iron_nugget":159,"minecraft:poppy":3,"minecraft:minecart":24,"minecraft:blue_shulker_box":34,"minecraft:sugar_cane":211,"minecraft:chest":8,"minecraft:phantom_membrane":61,"minecraft:raw_iron":54,"minecraft:copper_ingot":5,"minecraft:note_block":1,"minecraft:fire_charge":15,"minecraft:stone_button":2,"minecraft:trident":1,"minecraft:carrot":5,"minecraft:redstone":44,"minecraft:arrow":287,"minecraft:deepslate_bricks":89,"minecraft:hay_block":7,"minecraft:gold_ingot":277,"minecraft:rail":170,"minecraft:glow_ink_sac":57,"minecraft:leather":54,"minecraft:oak_log":21,"minecraft:ancient_debris":21,"minecraft:gunpowder":144,"minecraft:cobblestone_wall":12,"minecraft:cobblestone_stairs":7,"minecraft:paper":15,"minecraft:apple":1,"minecraft:stone_bricks":45,"minecraft:kelp":3,"minecraft:acacia_trapdoor":16,"minecraft:iron_ingot":279,"minecraft:soul_sand":118,"minecraft:acacia_sapling":8,"minecraft:book":15,"minecraft:smooth_basalt":12,"minecraft:stone_brick_slab":11,"minecraft:quartz":257,"minecraft:gravel":163,"minecraft:white_bed":3,"minecraft:crying_obsidian":17,"minecraft:spider_eye":175,"minecraft:slime_ball":11,"minecraft:polished_diorite":75,"minecraft:baked_potato":2,"minecraft:coal":11,"minecraft:hopper":2,"minecraft:ender_pearl":15},"minecraft:used":{"minecraft:polished_deepslate":7,"minecraft:iron_shovel":89,"minecraft:elytra":1,"minecraft:chest":25,"minecraft:stone":2,"minecraft:rotten_flesh":85,"minecraft:soul_sand":2,"minecraft:carrot":104,"minecraft:acacia_sapling":3,"minecraft:tuff":51,"minecraft:music_disc_13":1,"minecraft:glass":48,"minecraft:lava_bucket":4,"minecraft:lantern":4,"minecraft:stone_brick_stairs":40,"minecraft:stone_bricks":778,"minecraft:netherite_boots":2,"minecraft:birch_button":2,"minecraft:golden_sword":278,"minecraft:repeater":4,"minecraft:magma_block":1,"minecraft:bow":418,"minecraft:blue_shulker_box":36,"minecraft:furnace":4,"minecraft:cooked_cod":20,"minecraft:dark_oak_sapling":2,"minecraft:diorite":7,"minecraft:diamond_boots":1,"minecraft:dropper":7,"minecraft:oak_planks":4,"minecraft:chorus_fruit":17,"minecraft:acacia_trapdoor":22,"minecraft:powered_rail":61,"minecraft:ender_pearl":9,"minecraft:diamond_axe":83,"minecraft:sugar_cane":7,"minecraft:golden_apple":1,"minecraft:sand":125,"minecraft:netherite_leggings":2,"minecraft:netherite_helmet":2,"minecraft:note_block":1,"minecraft:redstone_torch":12,"minecraft:sticky_piston":10,"minecraft:lever":7,"minecraft:firework_rocket":178,"minecraft:acacia_door":1,"minecraft:stone_button":2,"minecraft:bread":66,"minecraft:gravel":82,"minecraft:diamond_sword":161,"minecraft:smithing_table":1,"minecraft:andesite":15,"minecraft:oak_boat":2,"minecraft:bone_meal":186,"minecraft:oak_trapdoor":1,"minecraft:netherite_sword":2956,"minecraft:trident":895,"minecraft:flint_and_steel":8,"minecraft:redstone":29,"minecraft:netherrack":736,"minecraft:torch":135,"minecraft:dirt":2366,"minecraft:anvil":3,"minecraft:hopper":11,"minecraft:cobblestone_wall":79,"minecraft:diamond_helmet":1,"minecraft:shulker_box":9,"minecraft:granite":24,"minecraft:polished_diorite":25,"minecraft:stone_brick_slab":22,"minecraft:bookshelf":5,"minecraft:barrel":1,"minecraft:smooth_basalt":7,"minecraft:bamboo":78,"minecraft:netherite_pickaxe":12387,"minecraft:minecart":20,"minecraft:stone_pressure_plate":1,"minecraft:cooked_beef":29,"minecraft:cobbled_deepslate":1,"minecraft:acacia_planks":1,"minecraft:observer":14,"minecraft:calcite":1,"minecraft:wheat_seeds":232,"minecraft:acacia_boat":2,"minecraft:water_bucket":76,"minecraft:cobblestone_stairs":45,"minecraft:rabbit":1,"minecraft:glass_bottle":22,"minecraft:netherite_chestplate":3,"minecraft:spruce_sign":2,"minecraft:cobblestone_slab":308,"minecraft:deepslate_bricks":1069,"minecraft:rail":394,"minecraft:music_disc_cat":1,"minecraft:crafting_table":7,"minecraft:white_bed":6,"minecraft:piston":1,"minecraft:activator_rail":1,"minecraft:diamond_pickaxe":9480,"minecraft:diamond_shovel":2739,"minecraft:acacia_sign":11,"minecraft:iron_pickaxe":4,"minecraft:detector_rail":33,"minecraft:spruce_trapdoor":2,"minecraft:fishing_rod":28,"minecraft:cobblestone":575,"minecraft:potion":1,"minecraft:white_banner":2,"minecraft:cooked_porkchop":20,"minecraft:bucket":97,"minecraft:diamond_leggings":1,"minecraft:splash_potion":2},"minecraft:mined":{"minecraft:white_bed":3,"minecraft:cobblestone_stairs":8,"minecraft:granite":39,"minecraft:acacia_log":45,"minecraft:grass_block":1498,"minecraft:soul_soil":11,"minecraft:deepslate_bricks":91,"minecraft:polished_diorite":12,"minecraft:hopper":2,"minecraft:nether_wart":1,"minecraft:magma_block":54,"minecraft:iron_ore":9,"minecraft:cobbled_deepslate":1,"minecraft:fire":7,"minecraft:deepslate_lapis_ore":39,"minecraft:dirt_path":11,"minecraft:deepslate_redstone_ore":3,"minecraft:blackstone":336,"minecraft:kelp_plant":1,"minecraft:soul_fire":17,"minecraft:note_block":1,"minecraft:torch":25,"minecraft:calcite":1,"minecraft:poppy":3,"minecraft:chest":8,"minecraft:glass":1,"minecraft:nether_quartz_ore":191,"minecraft:cobblestone":165,"minecraft:sugar_cane":122,"minecraft:wall_torch":26,"minecraft:warped_nylium":2,"minecraft:repeater":1,"minecraft:powered_rail":17,"minecraft:birch_log":1,"minecraft:wheat":86,"minecraft:activator_rail":1,"minecraft:stone_brick_stairs":24,"minecraft:grass":160,"minecraft:oak_log":16,"minecraft:sand":202,"minecraft:birch_button":1,"minecraft:dirt":1137,"minecraft:smooth_basalt":12,"minecraft:acacia_sign":1,"minecraft:blue_shulker_box":33,"minecraft:netherrack":18465,"minecraft:ancient_debris":21,"minecraft:oak_leaves":11,"minecraft:deepslate":947,"minecraft:nether_gold_ore":78,"minecraft:diamond_ore":1,"minecraft:tuff":71,"minecraft:deepslate_diamond_ore":34,"minecraft:shulker_box":8,"minecraft:lever":4,"minecraft:ladder":1,"minecraft:stone_button":1,"minecraft:redstone_wire":16,"minecraft:hay_block":7,"minecraft:redstone_ore":1,"minecraft:furnace":1,"minecraft:acacia_trapdoor":15,"minecraft:andesite":35,"minecraft:detector_rail":17,"minecraft:polished_deepslate":7,"minecraft:bookshelf":5,"minecraft:deepslate_iron_ore":18,"minecraft:cobblestone_slab":25,"minecraft:rail":59,"minecraft:bamboo_sapling":1,"minecraft:bamboo":32,"minecraft:stone":585,"minecraft:redstone_wall_torch":4,"minecraft:acacia_leaves":5,"minecraft:soul_sand":11,"minecraft:stone_brick_slab":8,"minecraft:basalt":364,"minecraft:observer":4,"minecraft:crafting_table":4,"minecraft:dropper":5,"minecraft:copper_ore":1,"minecraft:tall_grass":13,"minecraft:deepslate_gold_ore":7,"minecraft:diorite":16,"minecraft:warped_wart_block":1,"minecraft:cobblestone_wall":12,"minecraft:redstone_torch":3,"minecraft:gravel":49,"minecraft:acacia_door":1,"minecraft:cobweb":1,"minecraft:acacia_planks":1,"minecraft:stone_bricks":46,"minecraft:acacia_wall_sign":1},"minecraft:crafted":{"minecraft:oak_planks":20,"minecraft:cobblestone_slab":216,"minecraft:barrel":1,"minecraft:cobblestone_stairs":40,"minecraft:stone":540,"minecraft:lever":3,"minecraft:diamond_shovel":1,"minecraft:glass":64,"minecraft:hopper":2,"minecraft:stone_brick_slab":114,"minecraft:repeater":3,"minecraft:bow":5,"minecraft:stone_pressure_plate":5,"minecraft:chest":3,"minecraft:rail":272,"minecraft:birch_button":2,"minecraft:stone_bricks":832,"minecraft:golden_sword":1,"minecraft:glass_bottle":21,"minecraft:dropper":2,"minecraft:arrow":96,"minecraft:emerald":552,"minecraft:diamond_axe":2,"minecraft:crafting_table":5,"minecraft:smithing_table":1,"minecraft:sticky_piston":12,"minecraft:gold_block":341,"minecraft:birch_planks":4,"minecraft:stone_brick_stairs":28,"minecraft:dark_oak_sapling":2,"minecraft:book":28,"minecraft:paper":117,"minecraft:diamond_pickaxe":1,"minecraft:emerald_block":28,"minecraft:stick":64,"minecraft:iron_ingot":143,"minecraft:iron_block":9,"minecraft:gold_ingot":2630,"minecraft:redstone_torch":25,"minecraft:netherite_ingot":6,"minecraft:deepslate_bricks":980,"minecraft:furnace":1,"minecraft:stone_button":1,"minecraft:piston":12,"minecraft:pufferfish_bucket":1,"minecraft:bone_meal":186,"minecraft:blue_shulker_box":2,"minecraft:netherite_chestplate":1,"minecraft:detector_rail":18,"minecraft:polished_deepslate":930,"minecraft:slime_ball":5,"minecraft:ender_pearl":11,"minecraft:cobblestone_wall":120,"minecraft:diamond_boots":1,"minecraft:netherite_scrap":19,"minecraft:minecart":2,"minecraft:observer":10,"minecraft:wheat":63,"minecraft:cooked_cod":20,"minecraft:netherite_pickaxe":1,"minecraft:powered_rail":30,"minecraft:acacia_trapdoor":8,"minecraft:bucket":1,"minecraft:enchanted_book":15,"minecraft:acacia_boat":1,"minecraft:bread":65,"minecraft:air":0,"minecraft:blue_dye":11,"minecraft:oak_boat":1,"minecraft:white_wool":9,"minecraft:golden_apple":16,"minecraft:gold_nugget":24,"minecraft:acacia_sign":9,"minecraft:anvil":3,"minecraft:white_bed":3,"minecraft:note_block":1,"minecraft:acacia_planks":180,"minecraft:torch":40,"minecraft:lapis_block":58,"minecraft:firework_rocket":243}},"DataVersion":2865}